[
  {"id":1,"write":"We pay taxes."},
  {"id":2,"write":"Citizens can vote."},
  {"id":3,"write":"People want to vote."},
  {"id":4,"write":"Freedom of speech is a right."},
  {"id":5,"write":"The flag is red, white, and blue."},
  {"id":6,"write":"The flag has red and white stripes."},
  {"id":7,"write":"The President lives in the White House."},
  {"id":8,"write":"The White House is in Washington D.C."},
  {"id":9,"write":"Washington is the capital."},
  {"id":10,"write":"People vote for the President in November."},
  {"id":11,"write":"The President of the United States is elected by the people."},
  {"id":12,"write":"George Washington was the first President."},
  {"id":13,"write":"Delaware was the first state."},
  {"id":14,"write":"New York City was the first capital."},
  {"id":15,"write":"Washington is the Father of Our Country."},
  {"id":16,"write":"Washington is on the dollar bill."},
  {"id":17,"write":"Washington was the first President."},
  {"id":18,"write":"Adams was the second President."},
  {"id":19,"write":"Abraham Lincoln freed the slaves."},
  {"id":20,"write":"Lincoln was the President during the Civil War."},
  {"id":21,"write":"The people elect Congress."},
  {"id":22,"write":"We have one hundred Senators."},
  {"id":23,"write":"There are 100 Senators in the US Senate."},
  {"id":24,"write":"I live in the United States."},
  {"id":25,"write":"I love to live in America."},
  {"id":26,"write":"The American Indians lived here first."},
  {"id":27,"write":"Canada is north of the United States."},
  {"id":28,"write":"Mexico is south of the United States."},
  {"id":29,"write":"Presidents’ Day is in February."},
  {"id":30,"write":"Memorial Day is in May."},
  {"id":31,"write":"Flag Day is in June."},
  {"id":32,"write":"Independence Day is in July."},
  {"id":33,"write":"Labor Day is in September."},
  {"id":34,"write":"Columbus Day is in October."},
  {"id":35,"write":"Thanksgiving is in November."},
  {"id":36,"write":"California has largest population in the United States."},
  {"id":37,"write":"California has the most people."},
  {"id":38,"write":"Alaska is the largest U.S. state."},
  {"id":39,"write":"The United States has 50 states."},
  {"id":40,"write":"The 50 States and Washington, D.C."}
]